disdrodb/__init__.py
disdrodb/_config.py
disdrodb/_version.py
disdrodb/configs.py
disdrodb/constants.py
disdrodb/docs.py
disdrodb/accessor/__init__.py
disdrodb/accessor/methods.py
disdrodb/api/__init__.py
disdrodb/api/checks.py
disdrodb/api/configs.py
disdrodb/api/create_directories.py
disdrodb/api/info.py
disdrodb/api/io.py
disdrodb/api/path.py
disdrodb/api/search.py
disdrodb/cli/disdrodb_check_metadata_archive.py
disdrodb/cli/disdrodb_check_products_options.py
disdrodb/cli/disdrodb_create_summary.py
disdrodb/cli/disdrodb_create_summary_station.py
disdrodb/cli/disdrodb_data_archive_directory.py
disdrodb/cli/disdrodb_download_archive.py
disdrodb/cli/disdrodb_download_metadata_archive.py
disdrodb/cli/disdrodb_download_station.py
disdrodb/cli/disdrodb_initialize_station.py
disdrodb/cli/disdrodb_metadata_archive_directory.py
disdrodb/cli/disdrodb_open_data_archive.py
disdrodb/cli/disdrodb_open_logs_directory.py
disdrodb/cli/disdrodb_open_metadata_archive.py
disdrodb/cli/disdrodb_open_metadata_directory.py
disdrodb/cli/disdrodb_open_product_directory.py
disdrodb/cli/disdrodb_open_readers_directory.py
disdrodb/cli/disdrodb_run.py
disdrodb/cli/disdrodb_run_l0.py
disdrodb/cli/disdrodb_run_l0_station.py
disdrodb/cli/disdrodb_run_l0a.py
disdrodb/cli/disdrodb_run_l0a_station.py
disdrodb/cli/disdrodb_run_l0b.py
disdrodb/cli/disdrodb_run_l0b_station.py
disdrodb/cli/disdrodb_run_l0c.py
disdrodb/cli/disdrodb_run_l0c_station.py
disdrodb/cli/disdrodb_run_l1.py
disdrodb/cli/disdrodb_run_l1_station.py
disdrodb/cli/disdrodb_run_l2e.py
disdrodb/cli/disdrodb_run_l2e_station.py
disdrodb/cli/disdrodb_run_l2m.py
disdrodb/cli/disdrodb_run_l2m_station.py
disdrodb/cli/disdrodb_run_station.py
disdrodb/cli/disdrodb_upload_archive.py
disdrodb/cli/disdrodb_upload_station.py
disdrodb/data_transfer/__init__.py
disdrodb/data_transfer/download_data.py
disdrodb/data_transfer/upload_data.py
disdrodb/data_transfer/zenodo.py
disdrodb/etc/configs/attributes.yaml
disdrodb/etc/configs/encodings.yaml
disdrodb-0.3.0.dist-info/licenses/LICENSE
disdrodb-0.3.0.dist-info/METADATA
disdrodb-0.3.0.dist-info/WHEEL
disdrodb-0.3.0.dist-info/entry_points.txt
disdrodb-0.3.0.dist-info/top_level.txt
disdrodb-0.3.0.dist-info/RECORD
