Metadata-Version: 2.4
Name: disdrodb
Version: 0.3.0
Summary: disdrodb provides tools to download, standardize, share and analyze global disdrometer data.
Author: Gionata Ghiggi
Project-URL: homepage, https://github.com/ltelab/disdrodb
Project-URL: repository, https://github.com/ltelab/disdrodb
Project-URL: source, https://github.com/ltelab/disdrodb
Project-URL: tracker, https://github.com/ltelab/disdrodb/issues
Project-URL: documentation, https://disdrodb.readthedocs.io
Project-URL: changelog, https://github.com/ltelab/disdrodb/blob/main/CHANGELOG.md
Keywords: python,disdrometer,parsivel,drop size distribution
Classifier: Development Status :: 5 - Production/Stable
Classifier: Intended Audience :: Developers
Classifier: Programming Language :: Python :: 3
Classifier: Operating System :: Unix
Classifier: Operating System :: MacOS :: MacOS X
Classifier: Operating System :: Microsoft :: Windows
Requires-Python: >=3.9
License-File: LICENSE
Requires-Dist: click
Requires-Dist: tqdm
Requires-Dist: pooch
Requires-Dist: donfig
Requires-Dist: requests
Requires-Dist: PyYAML
Requires-Dist: trollsift
Requires-Dist: netCDF4
Requires-Dist: pyarrow
Requires-Dist: pandas
Requires-Dist: numpy
Requires-Dist: scipy
Requires-Dist: dask[distributed]
Requires-Dist: xarray
Requires-Dist: bottleneck
Requires-Dist: matplotlib
Provides-Extra: dev
Requires-Dist: jupyter; extra == "dev"
Requires-Dist: pre-commit; extra == "dev"
Requires-Dist: pytest; extra == "dev"
Requires-Dist: pydantic>=2.0.0; extra == "dev"
Requires-Dist: pytest-cov; extra == "dev"
Requires-Dist: pytest-mock; extra == "dev"
Requires-Dist: requests-mock; extra == "dev"
Requires-Dist: setuptools; extra == "dev"
Requires-Dist: build; extra == "dev"
Requires-Dist: twine; extra == "dev"
Requires-Dist: loghub; extra == "dev"
Dynamic: license-file
